code_generator/__init__.py
code_generator/config.py
code_generator/loader.py
code_generator/main.py
code_generator/render.py
code_generator/server.py
code_generator-0.0.8.dist-info/LICENSE
code_generator-0.0.8.dist-info/METADATA
code_generator-0.0.8.dist-info/WHEEL
code_generator-0.0.8.dist-info/entry_points.txt
code_generator-0.0.8.dist-info/top_level.txt
code_generator-0.0.8.dist-info/RECORD
