Metadata-Version: 2.1
Name: code-generator
Version: 0.0.8
Summary: a simple code generator for all-language
Home-page: UNKNOWN
Author: wj-Mcat
Author-email: 1435130236@qq.com
License: Apache 2
Keywords: code-gen,code-generator,python,code-snippet
Platform: UNKNOWN
Requires-Dist: flask
Requires-Dist: flask-cors
